LICENSE.txt
MANIFEST.in
README
README.rst
requirements.txt
setup.cfg
setup.py
pyfieri/__init__.py
pyfieri/data.json
pyfieri/guy_fieri.py
pyfieri.egg-info/PKG-INFO
pyfieri.egg-info/SOURCES.txt
pyfieri.egg-info/dependency_links.txt
pyfieri.egg-info/top_level.txt
pyfieri.egg-info/zip-safe
scripts/pyfieri