Metadata-Version: 1.1
Name: pyfieri
Version: 1.2.2
Summary: Guy Fieri Menu Item Generator
Home-page: http://nickficano.com
Author: Nick Ficano
Author-email: nficano@gmail.com
License: Copyright (c) 2015 Nick Ficano (http://nickficano.com)
